{
    "title": "The Romans",
    "air_date": "16 January 1965",
    "num_episodes": 4,
    "episode_titles": [
        "The Slave Traders",
        "All Roads Lead To Rome",
        "Conspiracy",
        "Inferno"
    ],
    "episode_duration": 25,
    "writers": [
        "Dennis Spooner"
    ],
    "directors": [
        "Christopher Barry"
    ],
    "media_format": "B_W",
    "dialogue_triumphs": [
        "Ian: 'I've got a friend who specialises in trouble. He dives in and usually finds a way.'",
        "Nero on the Doctor's silent pretend harping: 'He's all right, but he's not all that good.'"
    ],
    "dialogue_disasters": null,
    "goofs": [
        "William Hartnell keeps tripping over his lines, including keeping Michael Peake waiting for his cue until he goes for it anyway, and then interrupting him.",
        "Hartnell seems to tell a guard to 'sod off'.",
        "Ian and Barbara have a plastic-lined fountain.",
        "Nero pays his fire-starters in metal washers.",
        "Historically, Nero was in Actium, and the fire was almost certainly an accident.",
        "Nero was 26-28, not middle-aged, and Locusta, though real, was not an 'official poisoner'.",
        "The swords aren't the right shape, and wouldn't have been used with nets."
    ],
    "continuity_notes": [
        {
            "name": "TARDIS",
            "type": "Object",
            "description": "The Doctor's time machine and spacecraft",
            "origin": null,
            "current_status": "Can take off from any angle"
        },
        {
            "name": "The Doctor",
            "type": "Character",
            "description": "The main protagonist of the series",
            "origin": null,
            "current_status": "Can fight and enjoys pugilism, but can't play the lyre"
        },
        {
            "name": "Vicki",
            "type": "Character",
            "description": "One of the Doctor's companions",
            "origin": null,
            "current_status": "No good at dressmaking, but has a good grasp of history"
        }
    ],
    "technobabble": null,
    "roots": [
        "Spartacus",
        "Whitehall farces",
        "The Emperor's New Clothes"
    ],
    "links": [
        "Carnival of Monsters"
    ],
    "locations": [
        {
            "name": "Environs of Rome",
            "type": "Location",
            "description": "The area surrounding the city of Rome",
            "origin": "Earth",
            "current_status": "Setting of the story in July 64 AD"
        }
    ],
    "future_history": null,
    "untold_adventures": [
        "The Doctor has been to Rome before",
        "The Doctor once taught the Mountain Mauler of Montana",
        "The Doctor gave Hans Anderson the idea for 'The Emperor's New Clothes'"
    ],
    "qv": [
        "Changing History"
    ],
    "additional_notes": "Barbara and Ian frolic around the villa in very postcoital fashion, blissed-out on wine. The scene where Nero poisons his annoying slave, Tigilinus, is a delight. Being a comedy, Hartnell shows the talent that got him the part. His trouncing of the assassin is lovely.",
    "bottom_line": "Great Nero, good jokes, jolly atmosphere, marred by hints of historical realism."
}