{
    "title": "Warriors' Gate",
    "air_date": "3 January 1981",
    "num_episodes": 4,
    "episode_titles": [
        "Part One",
        "Part Two",
        "Part Three",
        "Part Four"
    ],
    "episode_duration": 25,
    "writers": [
        "Steve Gallagher"
    ],
    "directors": [
        "Paul Joyce"
    ],
    "media_format": "Color",
    "dialogue_triumphs": [
        "We'll burn that bridge when we come to it.",
        "You're a machine, aren't you? I usually get on so well with machines.",
        "Because he was running.",
        "I'm finally getting something done!",
        "They're only people."
    ],
    "dialogue_disasters": [
        "Astral Jung!",
        "The backblast backlash'll bounce back and destroy everything."
    ],
    "goofs": [
        "In episode two, a Gundan's axe falls onto the Doctor's back, without harm.",
        "In episode three, a boom-mike pokes out from behind the MZ.",
        "Adric takes K-9's ear, but when the dog arrives at the Doctor, it's got both.",
        "When Packard swings K-9 overhead, its hollow interior is visible.",
        "Lalla Ward has trouble pronouncing Romanadvoratrelundar."
    ],
    "continuity_notes": [
        {
            "name": "Romana",
            "type": "Character",
            "description": "Time Lord companion of the Doctor",
            "origin": "Gallifrey",
            "current_status": "Doesn't want to return to Gallifrey, leaves the Doctor to help the Tharils with time technology"
        },
        {
            "name": "K-9",
            "type": "Object",
            "description": "Robotic dog companion",
            "origin": null,
            "current_status": "Contains plans for all TARDIS functions"
        },
        {
            "name": "TARDIS",
            "type": "Object",
            "description": "The Doctor's time and space machine",
            "origin": "Gallifrey",
            "current_status": "Half the shelves in the TARDIS stores are empty"
        }
    ],
    "technobabble": [
        "Dwarf star material is impossible to collect"
    ],
    "roots": [
        "Rock video",
        "Waiting for Godot",
        "Rosencrantz and Guildenstern are Dead",
        "Frederick Pohl's Gateway",
        "I Ching",
        "Alien",
        "Star Trek's 'The City on the Edge of Forever'",
        "Julius Caesar",
        "Philip K. Dick's The Three Stigmata of Palmer Eldritch",
        "Alice in Wonderland",
        "Steve Gallagher's Dying of Paradise and The Babylon Run",
        "Jean Cocteau's La Belle et la B\u00eate and Orph\u00e9e"
    ],
    "links": [
        "Planet of the Spiders",
        "The Stones of Blood"
    ],
    "locations": [
        {
            "name": "Zero coordinates",
            "type": "Location",
            "description": "A plain surface micro-universe at the boundary of E- and N-space",
            "origin": "Created to serve as a defensive perimeter for the Tharil Empire",
            "current_status": "Setting of the story"
        }
    ],
    "future_history": "Humans use enslaved Tharils to navigate hyperspace, effectively travelling in time. The Tharil Empire used to exist in E-space, raiding N-space for human slaves, but the humans created the Gundans, who breached the Gate and destroyed the Empire.",
    "untold_adventures": null,
    "qv": null,
    "additional_notes": "A Tharil can walk the wind (possibly navigate the vortex) unharmed.",
    "bottom_line": "Praised for its direction, design, effects, music, and Romana's leaving scene. Notable elements include the coin, the gardens, and the banal villainy of the crew."
}